<annotation>
	<folder></folder>
	<filename>FudanPed00059_jpg.rf.ec85ee9b5ad8d675088e29730720c2e3.jpg</filename>
	<path>FudanPed00059_jpg.rf.ec85ee9b5ad8d675088e29730720c2e3.jpg</path>
	<source>
		<database>roboflow.ai</database>
	</source>
	<size>
		<width>412</width>
		<height>412</height>
		<depth>3</depth>
	</size>
	<segmented>0</segmented>
	<object>
		<name>ped</name>
		<pose>Unspecified</pose>
		<truncated>0</truncated>
		<difficult>0</difficult>
		<occluded>0</occluded>
		<bndbox>
			<xmin>25</xmin>
			<xmax>97</xmax>
			<ymin>59</ymin>
			<ymax>370</ymax>
		</bndbox>
	</object>
	<object>
		<name>ped</name>
		<pose>Unspecified</pose>
		<truncated>0</truncated>
		<difficult>0</difficult>
		<occluded>0</occluded>
		<bndbox>
			<xmin>114</xmin>
			<xmax>181</xmax>
			<ymin>37</ymin>
			<ymax>368</ymax>
		</bndbox>
	</object>
	<object>
		<name>ped</name>
		<pose>Unspecified</pose>
		<truncated>0</truncated>
		<difficult>0</difficult>
		<occluded>0</occluded>
		<bndbox>
			<xmin>194</xmin>
			<xmax>274</xmax>
			<ymin>48</ymin>
			<ymax>367</ymax>
		</bndbox>
	</object>
</annotation>
