<annotation>
	<folder></folder>
	<filename>FudanPed00047_jpg.rf.3eb4206368cd76e66d8bc481ecd2cb31.jpg</filename>
	<path>FudanPed00047_jpg.rf.3eb4206368cd76e66d8bc481ecd2cb31.jpg</path>
	<source>
		<database>roboflow.ai</database>
	</source>
	<size>
		<width>378</width>
		<height>378</height>
		<depth>3</depth>
	</size>
	<segmented>0</segmented>
	<object>
		<name>ped</name>
		<pose>Unspecified</pose>
		<truncated>0</truncated>
		<difficult>0</difficult>
		<occluded>0</occluded>
		<bndbox>
			<xmin>233</xmin>
			<xmax>320</xmax>
			<ymin>124</ymin>
			<ymax>351</ymax>
		</bndbox>
	</object>
	<object>
		<name>ped</name>
		<pose>Unspecified</pose>
		<truncated>0</truncated>
		<difficult>0</difficult>
		<occluded>0</occluded>
		<bndbox>
			<xmin>21</xmin>
			<xmax>73</xmax>
			<ymin>121</ymin>
			<ymax>307</ymax>
		</bndbox>
	</object>
	<object>
		<name>ped</name>
		<pose>Unspecified</pose>
		<truncated>0</truncated>
		<difficult>0</difficult>
		<occluded>0</occluded>
		<bndbox>
			<xmin>333</xmin>
			<xmax>373</xmax>
			<ymin>112</ymin>
			<ymax>203</ymax>
		</bndbox>
	</object>
</annotation>
