<annotation>
	<folder/>
	<filename>FudanPed00060.jpg</filename>
	<path>../../yolo//FudanPed00060.jpg</path>
	<source>
		<database>Unknown</database>
	</source>
	<size>
		<width>517</width>
		<height>440</height>
		<depth>3</depth>
	</size>
	<segmented>0</segmented>
	<object>
		<name>ped</name>
		<pose>Unspecified</pose>
		<truncated>0</truncated>
		<difficult>0</difficult>
		<bndbox>
			<xmin>187</xmin>
			<ymin>141</ymin>
			<xmax>290</xmax>
			<ymax>427</ymax>
		</bndbox>
	</object>
	<object>
		<name>ped</name>
		<pose>Unspecified</pose>
		<truncated>0</truncated>
		<difficult>0</difficult>
		<bndbox>
			<xmin>292</xmin>
			<ymin>130</ymin>
			<xmax>383</xmax>
			<ymax>430</ymax>
		</bndbox>
	</object>
	<object>
		<name>ped</name>
		<pose>Unspecified</pose>
		<truncated>0</truncated>
		<difficult>0</difficult>
		<bndbox>
			<xmin>394</xmin>
			<ymin>149</ymin>
			<xmax>497</xmax>
			<ymax>427</ymax>
		</bndbox>
	</object>
</annotation>
