<annotation>
	<folder/>
	<filename>PennPed00059.jpg</filename>
	<path>../../yolo//PennPed00059.jpg</path>
	<source>
		<database>Unknown</database>
	</source>
	<size>
		<width>582</width>
		<height>362</height>
		<depth>3</depth>
	</size>
	<segmented>0</segmented>
	<object>
		<name>ped</name>
		<pose>Unspecified</pose>
		<truncated>0</truncated>
		<difficult>0</difficult>
		<bndbox>
			<xmin>79</xmin>
			<ymin>43</ymin>
			<xmax>176</xmax>
			<ymax>336</ymax>
		</bndbox>
	</object>
	<object>
		<name>ped</name>
		<pose>Unspecified</pose>
		<truncated>0</truncated>
		<difficult>0</difficult>
		<bndbox>
			<xmin>381</xmin>
			<ymin>35</ymin>
			<xmax>529</xmax>
			<ymax>322</ymax>
		</bndbox>
	</object>
</annotation>
